asyncbs4/AsyncBeautifulSoup.py
asyncbs4/__init__.py
asyncbs4-1.0.4.dist-info/LICENSE
asyncbs4-1.0.4.dist-info/METADATA
asyncbs4-1.0.4.dist-info/WHEEL
asyncbs4-1.0.4.dist-info/top_level.txt
asyncbs4-1.0.4.dist-info/zip-safe
asyncbs4-1.0.4.dist-info/RECORD
