Metadata-Version: 2.1
Name: asyncbs4
Version: 1.0.4
Summary: Asynchronous BeautifulSoup Library.
Home-page: https://github.com/muntakim1/asyncBeautifulSoup
Author: Muntakimur rahaman
Author-email: muntakim1104001@gmail.com
License: MIT
Platform: UNKNOWN
Requires-Python: >=3.6
Requires-Dist: aiohttp
Requires-Dist: asyncio
Requires-Dist: bs4
